LICENSE
MANIFEST.in
README.md
setup.cfg
setup.py
easypqp/__init__.py
easypqp/convert.py
easypqp/library.py
easypqp/main.py
easypqp/openswathassaygenerator.py
easypqp/openswathdecoygenerator.py
easypqp/targetedfileconverter.py
easypqp/unimoddb.py
easypqp/util.py
easypqp/data/unimod.xml
fragpipe_speclib.egg-info/PKG-INFO
fragpipe_speclib.egg-info/SOURCES.txt
fragpipe_speclib.egg-info/dependency_links.txt
fragpipe_speclib.egg-info/entry_points.txt
fragpipe_speclib.egg-info/requires.txt
fragpipe_speclib.egg-info/top_level.txt
tests/test_convert.py
tests/test_generate_ionseries.py
tests/test_openswathassay_generator.py
tests/test_openswathdecoy_generator.py
tests/test_targetedfileconverter.py